setup.py
FaBo7Seg_TLC59208/TLC59208.py
FaBo7Seg_TLC59208/__init__.py
FaBo7Seg_TLC59208.egg-info/PKG-INFO
FaBo7Seg_TLC59208.egg-info/SOURCES.txt
FaBo7Seg_TLC59208.egg-info/dependency_links.txt
FaBo7Seg_TLC59208.egg-info/top_level.txt