Metadata-Version: 1.1
Name: FaBo7Seg-TLC59208
Version: 1.0.0
Summary: This is a library for the FaBo 7segment LED I2C Brick.
Home-page: https://github.com/FaBoPlatform/FaBo7Segment-TLC59208-Python
Author: FaBo
Author-email: info@fabo.io
License: Apache License 2.0
Platform: UNKNOWN
Classifier: Development Status :: 4 - Beta
Classifier: Operating System :: POSIX :: Linux
Classifier: License :: OSI Approved :: Apache Software License
Classifier: Intended Audience :: Developers
Classifier: Programming Language :: Python :: 2.7
Classifier: Topic :: Software Development
Classifier: Topic :: System :: Hardware
